mysoc2/rtl/dff.v
module dff (input d, input re, input we, input rstn, input clk, output reg q);

	reg value;
	always @(posedge clk or negedge rstn)
	begin
		if (!rstn) 
		begin 
			value <=0;
			q<=value;
		end
		else if (!re) value<=d;
		else if (!we) q<=value;
		//$display("value = 0x%0h",value);
	end
endmodule

mysoc2/sim/dff_tb.v
`include "dff.v"


`timescale 1ns/1ns

module dfftb();

	reg d;
	reg  re, we, rstn;
	reg clk;
	wire q;

	dff d1 (.d(d), .re(re), .we(we), .rstn(rstn), .clk(clk), .q(q));
	always #1 clk=~clk;


	initial begin
		$dumpfile("test.vcd");
		$dumpvars(0,dfftb);
		//$monitor("[monitor] time=%0t rstn=0x%0h d=0x%0h q=0x%0h re=0x%0h we=0x%0h", $time,rstn, d,q,re,we);
		$display("start: resetting flipflop");
		//reset
		re<=1; we<=1; rstn<=0; clk<=0; d<=0;
		#5;
		$display("clk=0x%0h",clk);
		#1;
		$display("time=%0t rstn=0x%0h d=0x%0h q=0x%0h re=0x%0h we=0x%0h", $time,rstn, d,q,re,we);
		$display("read from 'd' signal '1'");
		//read in 1 from 'd'
		rstn<=1; d<=1; re<=0;
		$display("clk=0x%0h",clk);
		#5;
		$display("time=%0t rstn=0x%0h d=0x%0h q=0x%0h re=0x%0h we=0x%0h", $time,rstn, d,q,re,we);
		$display("stop reading");
		re<=1;we<=1;
		#5;
		$display("time=%0t rstn=0x%0h d=0x%0h q=0x%0h re=0x%0h we=0x%0h", $time,rstn, d,q,re,we);
		//now q should have a value
		$display("write flipflop value out to q");
		we<=0;
		#5;
		$display("time=%0t rstn=0x%0h d=0x%0h q=0x%0h re=0x%0h we=0x%0h", $time,rstn, d,q,re,we);
		$display("turn off write enable");
		we<=1;
		#5;
		$display("time=%0t rstn=0x%0h d=0x%0h q=0x%0h re=0x%0h we=0x%0h", $time,rstn, d,q,re,we);
		$display("read and write, write should be a 1 and should read in a 0");
		re<=0;we<=0;d<=0;
		#5; 
		$display("time=%0t rstn=0x%0h d=0x%0h q=0x%0h re=0x%0h we=0x%0h", $time,rstn, d,q,re,we);
		$display("turn off read and set 'd' = 1");
		re<=1;d<=1;
		#5; 
		$display("time=%0t rstn=0x%0h d=0x%0h q=0x%0h re=0x%0h we=0x%0h", $time,rstn, d,q,re,we);
		$finish;
	end
endmodule

mysoc2/test.vcd
$date
	Wed Aug  4 01:22:16 2021
$end
$version
	Icarus Verilog
$end
$timescale
	1ns
$end
$scope module dfftb $end
$var wire 1 ! q $end
$var reg 1 " clk $end
$var reg 1 # d $end
$var reg 1 $ re $end
$var reg 1 % rstn $end
$var reg 1 & we $end
$scope module d1 $end
$var wire 1 " clk $end
$var wire 1 # d $end
$var wire 1 $ re $end
$var wire 1 % rstn $end
$var wire 1 & we $end
$var reg 1 ! q $end
$var reg 1 ' value $end
$upscope $end
$upscope $end
$enddefinitions $end
#0
$dumpvars
0'
1&
0%
1$
0#
0"
x!
$end
#1
0!
1"
#2
0"
#3
1"
#4
0"
#5
1"
#6
0$
1#
1%
0"
#7
1'
1"
#8
0"
#9
1"
#10
0"
#11
1$
1"
#12
0"
#13
1"
#14
0"
#15
1"
#16
0&
0"
#17
1!
1"
#18
0"
#19
1"
#20
0"
#21
1&
1"
#22
0"
#23
1"
#24
0"
#25
1"
#26
0#
0&
0$
0"
#27
0'
1"
#28
0"
#29
1"
#30
0"
#31
1#
1$
1"
#32
0"
#33
0!
1"
